MANIFEST.in
README
setup.py
contrib/quicktester.vim
quicktester/__init__.py
quicktester/fnmap.py
quicktester/git.py
quicktester/statistic.py
quicktester/util.py
quicktester.egg-info/PKG-INFO
quicktester.egg-info/SOURCES.txt
quicktester.egg-info/dependency_links.txt
quicktester.egg-info/entry_points.txt
quicktester.egg-info/top_level.txt
quicktester.egg-info/zip-safe
quicktester/plugin/__init__.py
quicktester/plugin/failonly.py
quicktester/plugin/git.py
quicktester/plugin/quickfix.py
quicktester/plugin/statistic.py