Metadata-Version: 1.1
Name: quicktester
Version: 0.5
Summary: quicktester nose plugin set
Home-page: http://github.com/herczy/quicktester
Author: Viktor Hercinger
Author-email: hercinger.viktor@gmail.com
License: BSD
Keywords: test unittest tdd vim quickfix relevant
Platform: UNKNOWN
Classifier: Development Status :: 4 - Beta
Classifier: Environment :: Console
Classifier: Intended Audience :: Developers
Classifier: License :: OSI Approved :: BSD License
Classifier: Natural Language :: English
Classifier: Operating System :: OS Independent
Classifier: Programming Language :: Python
Classifier: Programming Language :: Python :: 2
Classifier: Programming Language :: Python :: 2.7
Classifier: Programming Language :: Python :: 3
Classifier: Programming Language :: Python :: 3.3
Classifier: Programming Language :: Python :: 3.4
Classifier: Programming Language :: Python :: 3.5
Classifier: Topic :: Software Development :: Testing
Requires: nose
